{
  "swagger": "2.0",
  "info": {
    "title": "v1/machine.proto",
    "version": "version not set"
  },
  "tags": [
    {
      "name": "Machine"
    }
  ],
  "consumes": [
    "application/json"
  ],
  "produces": [
    "application/json"
  ],
  "paths": {},
  "definitions": {
    "protobufAny": {
      "type": "object",
      "properties": {
        "@type": {
          "type": "string"
        }
      },
      "additionalProperties": {}
    },
    "rpcStatus": {
      "type": "object",
      "properties": {
        "code": {
          "type": "integer",
          "format": "int32"
        },
        "message": {
          "type": "string"
        },
        "details": {
          "type": "array",
          "items": {
            "$ref": "#/definitions/protobufAny"
          }
        }
      }
    },
    "v1MachineReply": {
      "type": "object",
      "properties": {
        "machine": {
          "$ref": "#/definitions/v1MachineStruct"
        }
      }
    },
    "v1MachineStruct": {
      "type": "object",
      "properties": {
        "machineId": {
          "type": "string",
          "format": "int64"
        },
        "userId": {
          "type": "string",
          "format": "int64"
        },
        "address": {
          "type": "string"
        }
      }
    },
    "v1MachinesReply": {
      "type": "object",
      "properties": {
        "machines": {
          "type": "array",
          "items": {
            "$ref": "#/definitions/v1MachineStruct"
          }
        }
      }
    }
  }
}
